{
  "v": 1,
  "name": "Basandegi",
  "elevation_m": 625,
  "photo": "https://upload.wikimedia.org/wikipedia/commons/thumb/7/73/Dans_la_descente_du_port_d%27Otxondo%2C_en_direction_de_la_France._%C3%80_gauche_%2C_la_Rhune._Au_fond%2C_l%27Oc%C3%A9an_Atlantique._-_panoramio.jpg/1280px-Dans_la_descente_du_port_d%27Otxondo%2C_en_direction_de_la_France._%C3%80_gauche_%2C_la_Rhune._Au_fond%2C_l%27Oc%C3%A9an_Atlantique._-_panoramio.jpg",
  "photo_credit": "Gilles Guillamot · CC BY-SA 3.0",
  "source": "Photo : Wikimedia Commons"
}