{"v":1,"name":"Sreden Kamen","elevation_m":2456,"lat":42.01219,"lon":20.79211,"photo":"https://upload.wikimedia.org/wikipedia/commons/thumb/d/d5/%D0%A1%D1%80%D0%B5%D0%B4%D0%B5%D0%BD_%D0%9A%D0%B0%D0%BC%D0%B5%D0%BD_%28%D0%A8%D0%B0%D1%80_%D0%9F%D0%BB%D0%B0%D0%BD%D0%B8%D0%BD%D0%B0%29_01.jpg/1280px-%D0%A1%D1%80%D0%B5%D0%B4%D0%B5%D0%BD_%D0%9A%D0%B0%D0%BC%D0%B5%D0%BD_%28%D0%A8%D0%B0%D1%80_%D0%9F%D0%BB%D0%B0%D0%BD%D0%B8%D0%BD%D0%B0%29_01.jpg","photo_credit":"Wikimedia Commons","source":"Données publiques (Wikidata / Wikimedia Commons)"}